{
    "pilot": {
        "awscloudformation": {
            "AuthRoleName": "amplify-greenbrick-pilot-155958-authRole",
            "UnauthRoleArn": "arn:aws:iam::221943630936:role/amplify-greenbrick-pilot-155958-unauthRole",
            "AuthRoleArn": "arn:aws:iam::221943630936:role/amplify-greenbrick-pilot-155958-authRole",
            "Region": "eu-west-1",
            "DeploymentBucketName": "amplify-greenbrick-pilot-155958-deployment",
            "UnauthRoleName": "amplify-greenbrick-pilot-155958-unauthRole",
            "StackName": "amplify-greenbrick-pilot-155958",
            "StackId": "arn:aws:cloudformation:eu-west-1:221943630936:stack/amplify-greenbrick-pilot-155958/b20e8260-3047-11ed-bc0f-0ae54860a9fd",
            "AmplifyAppId": "dyzi7ktxd9k38"
        },
        "categories": {
            "hosting": {
                "amplifyhosting": {
                    "appId": "dyzi7ktxd9k38",
                    "type": "cicd"
                }
            }
        }
    }
}